dotbimpy/__init__.py
dotbimpy/file.py
dotbimpy-0.0.2.dist-info/LICENSE
dotbimpy-0.0.2.dist-info/METADATA
dotbimpy-0.0.2.dist-info/WHEEL
dotbimpy-0.0.2.dist-info/top_level.txt
dotbimpy-0.0.2.dist-info/RECORD
