Metadata-Version: 2.1
Name: dotbimpy
Version: 0.0.2
Summary: Python library for dotbim
Home-page: https://github.com/paireks/dotbimpy
Download-URL: https://github.com/paireks/dotbimpy/archive/refs/tags/v_0_0_2.tar.gz
Author: Wojciech
Author-email: w.radaczynski@gmail.com
License: MIT
Platform: UNKNOWN
Classifier: Development Status :: 3 - Alpha
Classifier: Intended Audience :: Developers
Classifier: Topic :: Software Development :: Build Tools
Classifier: License :: OSI Approved :: MIT License
Classifier: Programming Language :: Python :: 3.6
Classifier: Programming Language :: Python :: 3.7
Classifier: Programming Language :: Python :: 3.8
Classifier: Programming Language :: Python :: 3.9
License-File: LICENSE
Requires-Dist: jsonpickle
